sastra_male/__init__.py
sastra_male/knn_analysis.py
sastra_male-0.1.0.dist-info/METADATA
sastra_male-0.1.0.dist-info/WHEEL
sastra_male-0.1.0.dist-info/top_level.txt
sastra_male-0.1.0.dist-info/RECORD
